address_matcher/__init__.py
address_matcher/__main__.py
address_matcher/cli.py
address_matcher/demo.py
address_matcher/interactive_test.py
address_matcher/test_preprocessing.py
address_matcher/src/__init__.py
address_matcher/src/address_matcher.py
address_matcher/src/cli.py
address_matcher/src/data_loader.py
address_matcher/src/entity_extraction.py
address_matcher/src/fuzzy_matching.py
address_matcher/src/similarity.py
address_matcher/src/utils.py
indian_address_matcher-0.1.4.dist-info/LICENSE
indian_address_matcher-0.1.4.dist-info/METADATA
indian_address_matcher-0.1.4.dist-info/WHEEL
indian_address_matcher-0.1.4.dist-info/entry_points.txt
indian_address_matcher-0.1.4.dist-info/top_level.txt
indian_address_matcher-0.1.4.dist-info/RECORD
